{
	"source" : "http:\/\/lema.rae.es\/drae\/srv\/search?val=derretir",
	"word" : "derretir",
	"infinitivo" : "derretir",
	"participio" : [ "derretido" ],
	"gerundio" : [ "derritiendo" ],
	"tenses" : {
		"3" : [
			[ "derrito" ],
			[ "derrites", "derretís" ],
			[ "derrite" ],
			[ "derretimos" ],
			[ "derretís", "derriten" ],
			[ "derriten" ]
		],
		"4" : [
			[ "derretí" ],
			[ "derretiste" ],
			[ "derritió" ],
			[ "derretimos" ],
			[ "derretisteis", "derritieron" ],
			[ "derritieron" ]
		],
		"5" : [
			[ "derretía" ],
			[ "derretías" ],
			[ "derretía" ],
			[ "derretíamos" ],
			[ "derretíais", "derretían" ],
			[ "derretían" ]
		],
		"6" : [
			[ "derretiría" ],
			[ "derretirías" ],
			[ "derretiría" ],
			[ "derretiríamos" ],
			[ "derretiríais", "derretirían" ],
			[ "derretirían" ]
		],
		"7" : [
			[ "derretiré" ],
			[ "derretirás" ],
			[ "derretirá" ],
			[ "derretiremos" ],
			[ "derretiréis", "derretirán" ],
			[ "derretirán" ]
		],
		"8" : [
			[ "derrita" ],
			[ "derritas" ],
			[ "derrita" ],
			[ "derritamos" ],
			[ "derritáis", "derritan" ],
			[ "derritan" ]
		],
		"9" : [
			[ "derritiera" ],
			[ "derritieras" ],
			[ "derritiera" ],
			[ "derritiéramos" ],
			[ "derritierais", "derritieran" ],
			[ "derritieran" ]
		],
		"10" : [
			[ "derritiese" ],
			[ "derritieses" ],
			[ "derritiese" ],
			[ "derritiésemos" ],
			[ "derritieseis", "derritiesen" ],
			[ "derritiesen" ]
		],
		"11" : [
			[ "derritiere" ],
			[ "derritieres" ],
			[ "derritiere" ],
			[ "derritiéremos" ],
			[ "derritiereis", "derritieren" ],
			[ "derritieren" ]
		],
		"12" : {
			"1" : [ "derrite" ],
			"2" : [ "derrita" ],
			"3" : [ "derritamos" ],
			"4" : [ "derretid" ],
			"5" : [ "derritan" ]
		}
	}
}