{
	"source" : "http:\/\/www.spanishdict.com\/conjugate\/desabastecer",
	"word" : "desabastecer",
	"infinitivo" : "desabastecer",
	"gerundio" : [ "desabasteciendo" ],
	"participio" : [ "desabastecido" ],
	"tenses" : {
		"3" : [
			[ "desabastezco" ],
			[ "desabasteces" ],
			[ "desabastece" ],
			[ "desabastecemos" ],
			[ "desabastecéis" ],
			[ "desabastecen" ]
		],
		"4" : [
			[ "desabastecí" ],
			[ "desabasteciste" ],
			[ "desabasteció" ],
			[ "desabastecimos" ],
			[ "desabastecisteis" ],
			[ "desabastecieron" ]
		],
		"5" : [
			[ "desabastecía" ],
			[ "desabastecías" ],
			[ "desabastecía" ],
			[ "desabastecíamos" ],
			[ "desabastecíais" ],
			[ "desabastecían" ]
		],
		"6" : [
			[ "desabastecería" ],
			[ "desabastecerías" ],
			[ "desabastecería" ],
			[ "desabasteceríamos" ],
			[ "desabasteceríais" ],
			[ "desabastecerían" ]
		],
		"7" : [
			[ "desabasteceré" ],
			[ "desabastecerás" ],
			[ "desabastecerá" ],
			[ "desabasteceremos" ],
			[ "desabasteceréis" ],
			[ "desabastecerán" ]
		],
		"8" : [
			[ "desabastezca" ],
			[ "desabastezcas" ],
			[ "desabastezca" ],
			[ "desabastezcamos" ],
			[ "desabastezcáis" ],
			[ "desabastezcan" ]
		],
		"9" : [
			[ "desabasteciera" ],
			[ "desabastecieras" ],
			[ "desabasteciera" ],
			[ "desabasteciéramos" ],
			[ "desabastecierais" ],
			[ "desabastecieran" ]
		],
		"10" : [
			[ "desabasteciese" ],
			[ "desabastecieses" ],
			[ "desabasteciese" ],
			[ "desabasteciésemos" ],
			[ "desabastecieseis" ],
			[ "desabasteciesen" ]
		],
		"11" : [
			[ "desabasteciere" ],
			[ "desabastecieres" ],
			[ "desabasteciere" ],
			[ "desabasteciéremos" ],
			[ "desabasteciereis" ],
			[ "desabastecieren" ]
		],
		"12" : {
			"1" : [ "desabastece" ],
			"2" : [ "desabastezca" ],
			"3" : [ "desabastezcamos" ],
			"4" : [ "desabasteced" ],
			"5" : [ "desabastezcan" ]
		}
	}
}