{
	"source" : "http:\/\/www.spanishdict.com\/conjugate\/desvirtuar",
	"word" : "desvirtuar",
	"infinitivo" : "desvirtuar",
	"translation" : "to detract from",
	"gerundio" : [ "desvirtuando" ],
	"participio" : [ "desvirtuado" ],
	"tenses" : {
		"3" : [
			[ "desvirtúo" ],
			[ "desvirtúas" ],
			[ "desvirtúa" ],
			[ "desvirtuamos" ],
			[ "desvirtuáis" ],
			[ "desvirtúan" ]
		],
		"4" : [
			[ "desvirtué" ],
			[ "desvirtuaste" ],
			[ "desvirtuó" ],
			[ "desvirtuamos" ],
			[ "desvirtuasteis" ],
			[ "desvirtuaron" ]
		],
		"5" : [
			[ "desvirtuaba" ],
			[ "desvirtuabas" ],
			[ "desvirtuaba" ],
			[ "desvirtuábamos" ],
			[ "desvirtuabais" ],
			[ "desvirtuaban" ]
		],
		"6" : [
			[ "desvirtuaría" ],
			[ "desvirtuarías" ],
			[ "desvirtuaría" ],
			[ "desvirtuaríamos" ],
			[ "desvirtuaríais" ],
			[ "desvirtuarían" ]
		],
		"7" : [
			[ "desvirtuaré" ],
			[ "desvirtuarás" ],
			[ "desvirtuará" ],
			[ "desvirtuaremos" ],
			[ "desvirtuaréis" ],
			[ "desvirtuarán" ]
		],
		"8" : [
			[ "desvirtúe" ],
			[ "desvirtúes" ],
			[ "desvirtúe" ],
			[ "desvirtuemos" ],
			[ "desvirtuéis" ],
			[ "desvirtúen" ]
		],
		"9" : [
			[ "desvirtuara" ],
			[ "desvirtuaras" ],
			[ "desvirtuara" ],
			[ "desvirtuáramos" ],
			[ "desvirtuarais" ],
			[ "desvirtuaran" ]
		],
		"10" : [
			[ "desvirtuase" ],
			[ "desvirtuases" ],
			[ "desvirtuase" ],
			[ "desvirtuásemos" ],
			[ "desvirtuaseis" ],
			[ "desvirtuasen" ]
		],
		"11" : [
			[ "desvirtuare" ],
			[ "desvirtuares" ],
			[ "desvirtuare" ],
			[ "desvirtuáremos" ],
			[ "desvirtuareis" ],
			[ "desvirtuaren" ]
		],
		"12" : {
			"1" : [ "desvirtúa" ],
			"2" : [ "desvirtúe" ],
			"3" : [ "desvirtuemos" ],
			"4" : [ "desvirtuad" ],
			"5" : [ "desvirtúen" ]
		}
	}
}