{
	"source" : "http:\/\/www.spanishdict.com\/conjugate\/rebajar",
	"word" : "rebajar",
	"infinitivo" : "rebajar",
	"translation" : "to reduce, to lose weight, to lower oneself",
	"gerundio" : [ "rebajando" ],
	"participio" : [ "rebajado" ],
	"tenses" : {
		"3" : [
			[ "rebajo" ],
			[ "rebajas" ],
			[ "rebaja" ],
			[ "rebajamos" ],
			[ "rebajáis" ],
			[ "rebajan" ]
		],
		"4" : [
			[ "rebajé" ],
			[ "rebajaste" ],
			[ "rebajó" ],
			[ "rebajamos" ],
			[ "rebajasteis" ],
			[ "rebajaron" ]
		],
		"5" : [
			[ "rebajaba" ],
			[ "rebajabas" ],
			[ "rebajaba" ],
			[ "rebajábamos" ],
			[ "rebajabais" ],
			[ "rebajaban" ]
		],
		"6" : [
			[ "rebajaría" ],
			[ "rebajarías" ],
			[ "rebajaría" ],
			[ "rebajaríamos" ],
			[ "rebajaríais" ],
			[ "rebajarían" ]
		],
		"7" : [
			[ "rebajaré" ],
			[ "rebajarás" ],
			[ "rebajará" ],
			[ "rebajaremos" ],
			[ "rebajaréis" ],
			[ "rebajarán" ]
		],
		"8" : [
			[ "rebaje" ],
			[ "rebajes" ],
			[ "rebaje" ],
			[ "rebajemos" ],
			[ "rebajéis" ],
			[ "rebajen" ]
		],
		"9" : [
			[ "rebajara" ],
			[ "rebajaras" ],
			[ "rebajara" ],
			[ "rebajáramos" ],
			[ "rebajarais" ],
			[ "rebajaran" ]
		],
		"10" : [
			[ "rebajase" ],
			[ "rebajases" ],
			[ "rebajase" ],
			[ "rebajásemos" ],
			[ "rebajaseis" ],
			[ "rebajasen" ]
		],
		"11" : [
			[ "rebajare" ],
			[ "rebajares" ],
			[ "rebajare" ],
			[ "rebajáremos" ],
			[ "rebajareis" ],
			[ "rebajaren" ]
		],
		"12" : {
			"1" : [ "rebaja" ],
			"2" : [ "rebaje" ],
			"3" : [ "rebajemos" ],
			"4" : [ "rebajad" ],
			"5" : [ "rebajen" ]
		}
	}
}