{
	"source" : "http:\/\/www.spanishdict.com\/conjugate\/reflejar",
	"word" : "reflejar",
	"infinitivo" : "reflejar",
	"translation" : "to reflect, to be reflected",
	"gerundio" : [ "reflejando" ],
	"participio" : [ "reflejado" ],
	"tenses" : {
		"3" : [
			[ "reflejo" ],
			[ "reflejas" ],
			[ "refleja" ],
			[ "reflejamos" ],
			[ "reflejáis" ],
			[ "reflejan" ]
		],
		"4" : [
			[ "reflejé" ],
			[ "reflejaste" ],
			[ "reflejó" ],
			[ "reflejamos" ],
			[ "reflejasteis" ],
			[ "reflejaron" ]
		],
		"5" : [
			[ "reflejaba" ],
			[ "reflejabas" ],
			[ "reflejaba" ],
			[ "reflejábamos" ],
			[ "reflejabais" ],
			[ "reflejaban" ]
		],
		"6" : [
			[ "reflejaría" ],
			[ "reflejarías" ],
			[ "reflejaría" ],
			[ "reflejaríamos" ],
			[ "reflejaríais" ],
			[ "reflejarían" ]
		],
		"7" : [
			[ "reflejaré" ],
			[ "reflejarás" ],
			[ "reflejará" ],
			[ "reflejaremos" ],
			[ "reflejaréis" ],
			[ "reflejarán" ]
		],
		"8" : [
			[ "refleje" ],
			[ "reflejes" ],
			[ "refleje" ],
			[ "reflejemos" ],
			[ "reflejéis" ],
			[ "reflejen" ]
		],
		"9" : [
			[ "reflejara" ],
			[ "reflejaras" ],
			[ "reflejara" ],
			[ "reflejáramos" ],
			[ "reflejarais" ],
			[ "reflejaran" ]
		],
		"10" : [
			[ "reflejase" ],
			[ "reflejases" ],
			[ "reflejase" ],
			[ "reflejásemos" ],
			[ "reflejaseis" ],
			[ "reflejasen" ]
		],
		"11" : [
			[ "reflejare" ],
			[ "reflejares" ],
			[ "reflejare" ],
			[ "reflejáremos" ],
			[ "reflejareis" ],
			[ "reflejaren" ]
		],
		"12" : {
			"1" : [ "refleja" ],
			"2" : [ "refleje" ],
			"3" : [ "reflejemos" ],
			"4" : [ "reflejad" ],
			"5" : [ "reflejen" ]
		}
	}
}