{
	"source" : "http:\/\/www.spanishdict.com\/conjugate\/bastardear",
	"word" : "bastardear",
	"infinitivo" : "bastardear",
	"gerundio" : [ "bastardeando" ],
	"participio" : [ "bastardeado" ],
	"tenses" : {
		"3" : [
			[ "bastardeo" ],
			[ "bastardeas" ],
			[ "bastardea" ],
			[ "bastardeamos" ],
			[ "bastardeáis" ],
			[ "bastardean" ]
		],
		"4" : [
			[ "bastardeé" ],
			[ "bastardeaste" ],
			[ "bastardeó" ],
			[ "bastardeamos" ],
			[ "bastardeasteis" ],
			[ "bastardearon" ]
		],
		"5" : [
			[ "bastardeaba" ],
			[ "bastardeabas" ],
			[ "bastardeaba" ],
			[ "bastardeábamos" ],
			[ "bastardeabais" ],
			[ "bastardeaban" ]
		],
		"6" : [
			[ "bastardearía" ],
			[ "bastardearías" ],
			[ "bastardearía" ],
			[ "bastardearíamos" ],
			[ "bastardearíais" ],
			[ "bastardearían" ]
		],
		"7" : [
			[ "bastardearé" ],
			[ "bastardearás" ],
			[ "bastardeará" ],
			[ "bastardearemos" ],
			[ "bastardearéis" ],
			[ "bastardearán" ]
		],
		"8" : [
			[ "bastardee" ],
			[ "bastardees" ],
			[ "bastardee" ],
			[ "bastardeemos" ],
			[ "bastardeéis" ],
			[ "bastardeen" ]
		],
		"9" : [
			[ "bastardeara" ],
			[ "bastardearas" ],
			[ "bastardeara" ],
			[ "bastardeáramos" ],
			[ "bastardearais" ],
			[ "bastardearan" ]
		],
		"10" : [
			[ "bastardease" ],
			[ "bastardeases" ],
			[ "bastardease" ],
			[ "bastardeásemos" ],
			[ "bastardeaseis" ],
			[ "bastardeasen" ]
		],
		"11" : [
			[ "bastardeare" ],
			[ "bastardeares" ],
			[ "bastardeare" ],
			[ "bastardeáremos" ],
			[ "bastardeareis" ],
			[ "bastardearen" ]
		],
		"12" : {
			"1" : [ "bastardea" ],
			"2" : [ "bastardee" ],
			"3" : [ "bastardeemos" ],
			"4" : [ "bastardead" ],
			"5" : [ "bastardeen" ]
		}
	}
}