{
	"source" : "http:\/\/lema.rae.es\/drae\/srv\/search?val=languidecer",
	"word" : "languidecer",
	"infinitivo" : "languidecer",
	"participio" : [ "languidecido" ],
	"gerundio" : [ "languideciendo" ],
	"tenses" : {
		"3" : [
			[ "languidezco" ],
			[ "languideces", "languidecés" ],
			[ "languidece" ],
			[ "languidecemos" ],
			[ "languidecéis", "languidecen" ],
			[ "languidecen" ]
		],
		"4" : [
			[ "languidecí" ],
			[ "languideciste" ],
			[ "languideció" ],
			[ "languidecimos" ],
			[ "languidecisteis", "languidecieron" ],
			[ "languidecieron" ]
		],
		"5" : [
			[ "languidecía" ],
			[ "languidecías" ],
			[ "languidecía" ],
			[ "languidecíamos" ],
			[ "languidecíais", "languidecían" ],
			[ "languidecían" ]
		],
		"6" : [
			[ "languidecería" ],
			[ "languidecerías" ],
			[ "languidecería" ],
			[ "languideceríamos" ],
			[ "languideceríais", "languidecerían" ],
			[ "languidecerían" ]
		],
		"7" : [
			[ "languideceré" ],
			[ "languidecerás" ],
			[ "languidecerá" ],
			[ "languideceremos" ],
			[ "languideceréis", "languidecerán" ],
			[ "languidecerán" ]
		],
		"8" : [
			[ "languidezca" ],
			[ "languidezcas" ],
			[ "languidezca" ],
			[ "languidezcamos" ],
			[ "languidezcáis", "languidezcan" ],
			[ "languidezcan" ]
		],
		"9" : [
			[ "languideciera" ],
			[ "languidecieras" ],
			[ "languideciera" ],
			[ "languideciéramos" ],
			[ "languidecierais", "languidecieran" ],
			[ "languidecieran" ]
		],
		"10" : [
			[ "languideciese" ],
			[ "languidecieses" ],
			[ "languideciese" ],
			[ "languideciésemos" ],
			[ "languidecieseis", "languideciesen" ],
			[ "languideciesen" ]
		],
		"11" : [
			[ "languideciere" ],
			[ "languidecieres" ],
			[ "languideciere" ],
			[ "languideciéremos" ],
			[ "languideciereis", "languidecieren" ],
			[ "languidecieren" ]
		],
		"12" : {
			"1" : [ "languidece" ],
			"2" : [ "languidezca" ],
			"3" : [ "languidezcamos" ],
			"4" : [ "languideced" ],
			"5" : [ "languidezcan" ]
		}
	}
}