{
	"source" : "http:\/\/lema.rae.es\/drae\/srv\/search?val=tartamudear",
	"word" : "tartamudear",
	"infinitivo" : "tartamudear",
	"participio" : [ "tartamudeado" ],
	"gerundio" : [ "tartamudeando" ],
	"tenses" : {
		"3" : [
			[ "tartamudeo" ],
			[ "tartamudeas", "tartamudeás" ],
			[ "tartamudea" ],
			[ "tartamudeamos" ],
			[ "tartamudeáis", "tartamudean" ],
			[ "tartamudean" ]
		],
		"4" : [
			[ "tartamudeé" ],
			[ "tartamudeaste" ],
			[ "tartamudeó" ],
			[ "tartamudeamos" ],
			[ "tartamudeasteis", "tartamudearon" ],
			[ "tartamudearon" ]
		],
		"5" : [
			[ "tartamudeaba" ],
			[ "tartamudeabas" ],
			[ "tartamudeaba" ],
			[ "tartamudeábamos" ],
			[ "tartamudeabais", "tartamudeaban" ],
			[ "tartamudeaban" ]
		],
		"6" : [
			[ "tartamudearía" ],
			[ "tartamudearías" ],
			[ "tartamudearía" ],
			[ "tartamudearíamos" ],
			[ "tartamudearíais", "tartamudearían" ],
			[ "tartamudearían" ]
		],
		"7" : [
			[ "tartamudearé" ],
			[ "tartamudearás" ],
			[ "tartamudeará" ],
			[ "tartamudearemos" ],
			[ "tartamudearéis", "tartamudearán" ],
			[ "tartamudearán" ]
		],
		"8" : [
			[ "tartamudee" ],
			[ "tartamudees" ],
			[ "tartamudee" ],
			[ "tartamudeemos" ],
			[ "tartamudeéis", "tartamudeen" ],
			[ "tartamudeen" ]
		],
		"9" : [
			[ "tartamudeara" ],
			[ "tartamudearas" ],
			[ "tartamudeara" ],
			[ "tartamudeáramos" ],
			[ "tartamudearais", "tartamudearan" ],
			[ "tartamudearan" ]
		],
		"10" : [
			[ "tartamudease" ],
			[ "tartamudeases" ],
			[ "tartamudease" ],
			[ "tartamudeásemos" ],
			[ "tartamudeaseis", "tartamudeasen" ],
			[ "tartamudeasen" ]
		],
		"11" : [
			[ "tartamudeare" ],
			[ "tartamudeares" ],
			[ "tartamudeare" ],
			[ "tartamudeáremos" ],
			[ "tartamudeareis", "tartamudearen" ],
			[ "tartamudearen" ]
		],
		"12" : {
			"1" : [ "tartamudea" ],
			"2" : [ "tartamudee" ],
			"3" : [ "tartamudeemos" ],
			"4" : [ "tartamudead" ],
			"5" : [ "tartamudeen" ]
		}
	}
}