{
	"source" : "http:\/\/www.spanishdict.com\/conjugate\/calarse",
	"word" : "calarse",
	"infinitivo" : "calar",
	"translation" : "to soak; to penetrate",
	"gerundio" : [ "calando" ],
	"participio" : [ "calado" ],
	"tenses" : {
		"3" : [
			[ "me calo" ],
			[ "te calas" ],
			[ "se cala" ],
			[ "nos calamos" ],
			[ "os caláis" ],
			[ "se calan" ]
		],
		"4" : [
			[ "me calé" ],
			[ "te calaste" ],
			[ "se caló" ],
			[ "nos calamos" ],
			[ "os calasteis" ],
			[ "se calaron" ]
		],
		"5" : [
			[ "me calaba" ],
			[ "te calabas" ],
			[ "se calaba" ],
			[ "nos calábamos" ],
			[ "os calabais" ],
			[ "se calaban" ]
		],
		"6" : [
			[ "me calaría" ],
			[ "te calarías" ],
			[ "se calaría" ],
			[ "nos calaríamos" ],
			[ "os calaríais" ],
			[ "se calarían" ]
		],
		"7" : [
			[ "me calaré" ],
			[ "te calarás" ],
			[ "se calará" ],
			[ "nos calaremos" ],
			[ "os calaréis" ],
			[ "se calarán" ]
		],
		"8" : [
			[ "me cale" ],
			[ "te cales" ],
			[ "se cale" ],
			[ "nos calemos" ],
			[ "os caléis" ],
			[ "se calen" ]
		],
		"9" : [
			[ "me calara" ],
			[ "te calaras" ],
			[ "se calara" ],
			[ "nos caláramos" ],
			[ "os calarais" ],
			[ "se calaran" ]
		],
		"10" : [
			[ "me calase" ],
			[ "te calases" ],
			[ "se calase" ],
			[ "nos calásemos" ],
			[ "os calaseis" ],
			[ "se calasen" ]
		],
		"11" : [
			[ "me calare" ],
			[ "te calares" ],
			[ "se calare" ],
			[ "nos caláremos" ],
			[ "os calareis" ],
			[ "se calaren" ]
		],
		"12" : {
			"1" : [ "cala" ],
			"2" : [ "cale" ],
			"3" : [ "calemos" ],
			"4" : [ "calad" ],
			"5" : [ "calen" ]
		}
	}
}