{
	"source" : "http:\/\/www.spanishdict.com\/conjugate\/canturrear",
	"word" : "canturrear",
	"infinitivo" : "canturrear",
	"translation" : "to hum",
	"gerundio" : [ "canturreando" ],
	"participio" : [ "canturreado" ],
	"tenses" : {
		"3" : [
			[ "canturreo" ],
			[ "canturreas" ],
			[ "canturrea" ],
			[ "canturreamos" ],
			[ "canturreáis" ],
			[ "canturrean" ]
		],
		"4" : [
			[ "canturreé" ],
			[ "canturreaste" ],
			[ "canturreó" ],
			[ "canturreamos" ],
			[ "canturreasteis" ],
			[ "canturrearon" ]
		],
		"5" : [
			[ "canturreaba" ],
			[ "canturreabas" ],
			[ "canturreaba" ],
			[ "canturreábamos" ],
			[ "canturreabais" ],
			[ "canturreaban" ]
		],
		"6" : [
			[ "canturrearía" ],
			[ "canturrearías" ],
			[ "canturrearía" ],
			[ "canturrearíamos" ],
			[ "canturrearíais" ],
			[ "canturrearían" ]
		],
		"7" : [
			[ "canturrearé" ],
			[ "canturrearás" ],
			[ "canturreará" ],
			[ "canturrearemos" ],
			[ "canturrearéis" ],
			[ "canturrearán" ]
		],
		"8" : [
			[ "canturree" ],
			[ "canturrees" ],
			[ "canturree" ],
			[ "canturreemos" ],
			[ "canturreéis" ],
			[ "canturreen" ]
		],
		"9" : [
			[ "canturreara" ],
			[ "canturrearas" ],
			[ "canturreara" ],
			[ "canturreáramos" ],
			[ "canturrearais" ],
			[ "canturrearan" ]
		],
		"10" : [
			[ "canturrease" ],
			[ "canturreases" ],
			[ "canturrease" ],
			[ "canturreásemos" ],
			[ "canturreaseis" ],
			[ "canturreasen" ]
		],
		"11" : [
			[ "canturreare" ],
			[ "canturreares" ],
			[ "canturreare" ],
			[ "canturreáremos" ],
			[ "canturreareis" ],
			[ "canturrearen" ]
		],
		"12" : {
			"1" : [ "canturrea" ],
			"2" : [ "canturree" ],
			"3" : [ "canturreemos" ],
			"4" : [ "canturread" ],
			"5" : [ "canturreen" ]
		}
	}
}