{
	"source" : "http:\/\/www.spanishdict.com\/conjugate\/cohesionar",
	"word" : "cohesionar",
	"infinitivo" : "cohesionar",
	"gerundio" : [ "cohesionando" ],
	"participio" : [ "cohesionado" ],
	"tenses" : {
		"3" : [
			[ "cohesiono" ],
			[ "cohesionas" ],
			[ "cohesiona" ],
			[ "cohesionamos" ],
			[ "cohesionáis" ],
			[ "cohesionan" ]
		],
		"4" : [
			[ "cohesioné" ],
			[ "cohesionaste" ],
			[ "cohesionó" ],
			[ "cohesionamos" ],
			[ "cohesionasteis" ],
			[ "cohesionaron" ]
		],
		"5" : [
			[ "cohesionaba" ],
			[ "cohesionabas" ],
			[ "cohesionaba" ],
			[ "cohesionábamos" ],
			[ "cohesionabais" ],
			[ "cohesionaban" ]
		],
		"6" : [
			[ "cohesionaría" ],
			[ "cohesionarías" ],
			[ "cohesionaría" ],
			[ "cohesionaríamos" ],
			[ "cohesionaríais" ],
			[ "cohesionarían" ]
		],
		"7" : [
			[ "cohesionaré" ],
			[ "cohesionarás" ],
			[ "cohesionará" ],
			[ "cohesionaremos" ],
			[ "cohesionaréis" ],
			[ "cohesionarán" ]
		],
		"8" : [
			[ "cohesione" ],
			[ "cohesiones" ],
			[ "cohesione" ],
			[ "cohesionemos" ],
			[ "cohesionéis" ],
			[ "cohesionen" ]
		],
		"9" : [
			[ "cohesionara" ],
			[ "cohesionaras" ],
			[ "cohesionara" ],
			[ "cohesionáramos" ],
			[ "cohesionarais" ],
			[ "cohesionaran" ]
		],
		"10" : [
			[ "cohesionase" ],
			[ "cohesionases" ],
			[ "cohesionase" ],
			[ "cohesionásemos" ],
			[ "cohesionaseis" ],
			[ "cohesionasen" ]
		],
		"11" : [
			[ "cohesionare" ],
			[ "cohesionares" ],
			[ "cohesionare" ],
			[ "cohesionáremos" ],
			[ "cohesionareis" ],
			[ "cohesionaren" ]
		],
		"12" : {
			"1" : [ "cohesiona" ],
			"2" : [ "cohesione" ],
			"3" : [ "cohesionemos" ],
			"4" : [ "cohesionad" ],
			"5" : [ "cohesionen" ]
		}
	}
}