{
	"source" : "http:\/\/lema.rae.es\/drae\/srv\/search?val=compenetrarse",
	"word" : "compenetrarse",
	"infinitivo" : "compenetrarse",
	"participio" : [ "compenetrado" ],
	"gerundio" : [ "compenetrándome", "compenetrándote" ],
	"tenses" : {
		"3" : [
			[ "me compenetro" ],
			[ "te compenetras", "te compenetrás" ],
			[ "se compenetra" ],
			[ "nos compenetramos" ],
			[ "os compenetráis", "se compenetran" ],
			[ "se compenetran" ]
		],
		"4" : [
			[ "me compenetré" ],
			[ "te compenetraste" ],
			[ "se compenetró" ],
			[ "nos compenetramos" ],
			[ "os compenetrasteis", "se compenetraron" ],
			[ "se compenetraron" ]
		],
		"5" : [
			[ "me compenetraba" ],
			[ "te compenetrabas" ],
			[ "se compenetraba" ],
			[ "nos compenetrábamos" ],
			[ "os compenetrabais", "se compenetraban" ],
			[ "se compenetraban" ]
		],
		"6" : [
			[ "me compenetraría" ],
			[ "te compenetrarías" ],
			[ "se compenetraría" ],
			[ "nos compenetraríamos" ],
			[ "os compenetraríais", "se compenetrarían" ],
			[ "se compenetrarían" ]
		],
		"7" : [
			[ "me compenetraré" ],
			[ "te compenetrarás" ],
			[ "se compenetrará" ],
			[ "nos compenetraremos" ],
			[ "os compenetraréis", "se compenetrarán" ],
			[ "se compenetrarán" ]
		],
		"8" : [
			[ "me compenetre" ],
			[ "te compenetres" ],
			[ "se compenetre" ],
			[ "nos compenetremos" ],
			[ "os compenetréis", "se compenetren" ],
			[ "se compenetren" ]
		],
		"9" : [
			[ "me compenetrara" ],
			[ "te compenetraras" ],
			[ "se compenetrara" ],
			[ "nos compenetráramos" ],
			[ "os compenetrarais", "se compenetraran" ],
			[ "se compenetraran" ]
		],
		"10" : [
			[ "me compenetrase" ],
			[ "te compenetrases" ],
			[ "se compenetrase" ],
			[ "nos compenetrásemos" ],
			[ "os compenetraseis", "se compenetrasen" ],
			[ "se compenetrasen" ]
		],
		"11" : [
			[ "me compenetrare" ],
			[ "te compenetrares" ],
			[ "se compenetrare" ],
			[ "nos compenetráremos" ],
			[ "os compenetrareis", "se compenetraren" ],
			[ "se compenetraren" ]
		],
		"12" : {
			"1" : [ "compenétrate" ],
			"2" : [ "compenetre" ],
			"3" : [ "compenetremos" ],
			"4" : [ "compenetraos" ],
			"5" : [ "compenétrense" ]
		}
	}
}