{
	"source" : "http:\/\/www.spanishdict.com\/conjugate\/prostituir",
	"word" : "prostituir",
	"infinitivo" : "prostituir",
	"gerundio" : [ "prostituyendo" ],
	"participio" : [ "prostituido" ],
	"tenses" : {
		"3" : [
			[ "prostituyo" ],
			[ "prostituyes" ],
			[ "prostituye" ],
			[ "prostituimos" ],
			[ "prostituís" ],
			[ "prostituyen" ]
		],
		"4" : [
			[ "prostituí" ],
			[ "prostituiste" ],
			[ "prostituyó" ],
			[ "prostituimos" ],
			[ "prostituisteis" ],
			[ "prostituyeron" ]
		],
		"5" : [
			[ "prostituía" ],
			[ "prostituías" ],
			[ "prostituía" ],
			[ "prostituíamos" ],
			[ "prostituíais" ],
			[ "prostituían" ]
		],
		"6" : [
			[ "prostituiría" ],
			[ "prostituirías" ],
			[ "prostituiría" ],
			[ "prostituiríamos" ],
			[ "prostituiríais" ],
			[ "prostituirían" ]
		],
		"7" : [
			[ "prostituiré" ],
			[ "prostituirás" ],
			[ "prostituirá" ],
			[ "prostituiremos" ],
			[ "prostituiréis" ],
			[ "prostituirán" ]
		],
		"8" : [
			[ "prostituya" ],
			[ "prostituyas" ],
			[ "prostituya" ],
			[ "prostituyamos" ],
			[ "prostituyáis" ],
			[ "prostituyan" ]
		],
		"9" : [
			[ "prostituyera" ],
			[ "prostituyeras" ],
			[ "prostituyera" ],
			[ "prostituyéramos" ],
			[ "prostituyerais" ],
			[ "prostituyeran" ]
		],
		"10" : [
			[ "prostituyese" ],
			[ "prostituyeses" ],
			[ "prostituyese" ],
			[ "prostituyésemos" ],
			[ "prostituyeseis" ],
			[ "prostituyesen" ]
		],
		"11" : [
			[ "prostituyere" ],
			[ "prostituyeres" ],
			[ "prostituyere" ],
			[ "prostituyéremos" ],
			[ "prostituyereis" ],
			[ "prostituyeren" ]
		],
		"12" : {
			"1" : [ "prostituye" ],
			"2" : [ "prostituya" ],
			"3" : [ "prostituyamos" ],
			"4" : [ "prostituid" ],
			"5" : [ "prostituyan" ]
		}
	}
}