{
	"source" : "http:\/\/www.spanishdict.com\/conjugate\/armarse",
	"word" : "armarse",
	"infinitivo" : "armar",
	"translation" : "to arm oneself",
	"gerundio" : [ "armando" ],
	"participio" : [ "armado" ],
	"tenses" : {
		"3" : [
			[ "me armo" ],
			[ "te armas" ],
			[ "se arma" ],
			[ "nos armamos" ],
			[ "os armáis" ],
			[ "se arman" ]
		],
		"4" : [
			[ "me armé" ],
			[ "te armaste" ],
			[ "se armó" ],
			[ "nos armamos" ],
			[ "os armasteis" ],
			[ "se armaron" ]
		],
		"5" : [
			[ "me armaba" ],
			[ "te armabas" ],
			[ "se armaba" ],
			[ "nos armábamos" ],
			[ "os armabais" ],
			[ "se armaban" ]
		],
		"6" : [
			[ "me armaría" ],
			[ "te armarías" ],
			[ "se armaría" ],
			[ "nos armaríamos" ],
			[ "os armaríais" ],
			[ "se armarían" ]
		],
		"7" : [
			[ "me armaré" ],
			[ "te armarás" ],
			[ "se armará" ],
			[ "nos armaremos" ],
			[ "os armaréis" ],
			[ "se armarán" ]
		],
		"8" : [
			[ "me arme" ],
			[ "te armes" ],
			[ "se arme" ],
			[ "nos armemos" ],
			[ "os arméis" ],
			[ "se armen" ]
		],
		"9" : [
			[ "me armara" ],
			[ "te armaras" ],
			[ "se armara" ],
			[ "nos armáramos" ],
			[ "os armarais" ],
			[ "se armaran" ]
		],
		"10" : [
			[ "me armase" ],
			[ "te armases" ],
			[ "se armase" ],
			[ "nos armásemos" ],
			[ "os armaseis" ],
			[ "se armasen" ]
		],
		"11" : [
			[ "me armare" ],
			[ "te armares" ],
			[ "se armare" ],
			[ "nos armáremos" ],
			[ "os armareis" ],
			[ "se armaren" ]
		],
		"12" : {
			"1" : [ "arma" ],
			"2" : [ "arme" ],
			"3" : [ "armemos" ],
			"4" : [ "armad" ],
			"5" : [ "armen" ]
		}
	}
}