{
	"source" : "http:\/\/lema.rae.es\/drae\/srv\/search?val=arremangar",
	"word" : "arremangar",
	"infinitivo" : "arremangar",
	"participio" : [ "arremangado" ],
	"gerundio" : [ "arremangando" ],
	"tenses" : {
		"3" : [
			[ "arremango" ],
			[ "arremangas", "arremangás" ],
			[ "arremanga" ],
			[ "arremangamos" ],
			[ "arremangáis", "arremangan" ],
			[ "arremangan" ]
		],
		"4" : [
			[ "arremangué" ],
			[ "arremangaste" ],
			[ "arremangó" ],
			[ "arremangamos" ],
			[ "arremangasteis", "arremangaron" ],
			[ "arremangaron" ]
		],
		"5" : [
			[ "arremangaba" ],
			[ "arremangabas" ],
			[ "arremangaba" ],
			[ "arremangábamos" ],
			[ "arremangabais", "arremangaban" ],
			[ "arremangaban" ]
		],
		"6" : [
			[ "arremangaría" ],
			[ "arremangarías" ],
			[ "arremangaría" ],
			[ "arremangaríamos" ],
			[ "arremangaríais", "arremangarían" ],
			[ "arremangarían" ]
		],
		"7" : [
			[ "arremangaré" ],
			[ "arremangarás" ],
			[ "arremangará" ],
			[ "arremangaremos" ],
			[ "arremangaréis", "arremangarán" ],
			[ "arremangarán" ]
		],
		"8" : [
			[ "arremangue" ],
			[ "arremangues" ],
			[ "arremangue" ],
			[ "arremanguemos" ],
			[ "arremanguéis", "arremanguen" ],
			[ "arremanguen" ]
		],
		"9" : [
			[ "arremangara" ],
			[ "arremangaras" ],
			[ "arremangara" ],
			[ "arremangáramos" ],
			[ "arremangarais", "arremangaran" ],
			[ "arremangaran" ]
		],
		"10" : [
			[ "arremangase" ],
			[ "arremangases" ],
			[ "arremangase" ],
			[ "arremangásemos" ],
			[ "arremangaseis", "arremangasen" ],
			[ "arremangasen" ]
		],
		"11" : [
			[ "arremangare" ],
			[ "arremangares" ],
			[ "arremangare" ],
			[ "arremangáremos" ],
			[ "arremangareis", "arremangaren" ],
			[ "arremangaren" ]
		],
		"12" : {
			"1" : [ "arremanga" ],
			"2" : [ "arremangue" ],
			"3" : [ "arremanguemos" ],
			"4" : [ "arremangad" ],
			"5" : [ "arremanguen" ]
		}
	}
}