{
	"source" : "http:\/\/lema.rae.es\/drae\/srv\/search?val=arrigirse",
	"word" : "arrigirse",
	"infinitivo" : "arrigirse",
	"participio" : [ "arrigido" ],
	"gerundio" : [ "arrigiéndome", "arrigiéndote" ],
	"tenses" : {
		"3" : [
			[ "me arrijo" ],
			[ "te arriges", "te arrigís" ],
			[ "se arrige" ],
			[ "nos arrigimos" ],
			[ "os arrigís", "se arrigen" ],
			[ "se arrigen" ]
		],
		"4" : [
			[ "me arrigí" ],
			[ "te arrigiste" ],
			[ "se arrigió" ],
			[ "nos arrigimos" ],
			[ "os arrigisteis", "se arrigieron" ],
			[ "se arrigieron" ]
		],
		"5" : [
			[ "me arrigía" ],
			[ "te arrigías" ],
			[ "se arrigía" ],
			[ "nos arrigíamos" ],
			[ "os arrigíais", "se arrigían" ],
			[ "se arrigían" ]
		],
		"6" : [
			[ "me arrigiría" ],
			[ "te arrigirías" ],
			[ "se arrigiría" ],
			[ "nos arrigiríamos" ],
			[ "os arrigiríais", "se arrigirían" ],
			[ "se arrigirían" ]
		],
		"7" : [
			[ "me arrigiré" ],
			[ "te arrigirás" ],
			[ "se arrigirá" ],
			[ "nos arrigiremos" ],
			[ "os arrigiréis", "se arrigirán" ],
			[ "se arrigirán" ]
		],
		"8" : [
			[ "me arrija" ],
			[ "te arrijas" ],
			[ "se arrija" ],
			[ "nos arrijamos" ],
			[ "os arrijáis", "se arrijan" ],
			[ "se arrijan" ]
		],
		"9" : [
			[ "me arrigiera" ],
			[ "te arrigieras" ],
			[ "se arrigiera" ],
			[ "nos arrigiéramos" ],
			[ "os arrigierais", "se arrigieran" ],
			[ "se arrigieran" ]
		],
		"10" : [
			[ "me arrigiese" ],
			[ "te arrigieses" ],
			[ "se arrigiese" ],
			[ "nos arrigiésemos" ],
			[ "os arrigieseis", "se arrigiesen" ],
			[ "se arrigiesen" ]
		],
		"11" : [
			[ "me arrigiere" ],
			[ "te arrigieres" ],
			[ "se arrigiere" ],
			[ "nos arrigiéremos" ],
			[ "os arrigiereis", "se arrigieren" ],
			[ "se arrigieren" ]
		],
		"12" : {
			"1" : [ "arrígete" ],
			"2" : [ "arrija" ],
			"3" : [ "arrijamos" ],
			"4" : [ "arrigíos" ],
			"5" : [ "arríjanse" ]
		}
	}
}