{
	"source" : "http:\/\/www.spanishdict.com\/conjugate\/sacrificar",
	"word" : "sacrificar",
	"infinitivo" : "sacrificar",
	"translation" : "to sacrifice",
	"gerundio" : [ "sacrificando" ],
	"participio" : [ "sacrificado" ],
	"tenses" : {
		"3" : [
			[ "sacrifico" ],
			[ "sacrificas" ],
			[ "sacrifica" ],
			[ "sacrificamos" ],
			[ "sacrificáis" ],
			[ "sacrifican" ]
		],
		"4" : [
			[ "sacrifiqué" ],
			[ "sacrificaste" ],
			[ "sacrificó" ],
			[ "sacrificamos" ],
			[ "sacrificasteis" ],
			[ "sacrificaron" ]
		],
		"5" : [
			[ "sacrificaba" ],
			[ "sacrificabas" ],
			[ "sacrificaba" ],
			[ "sacrificábamos" ],
			[ "sacrificabais" ],
			[ "sacrificaban" ]
		],
		"6" : [
			[ "sacrificaría" ],
			[ "sacrificarías" ],
			[ "sacrificaría" ],
			[ "sacrificaríamos" ],
			[ "sacrificaríais" ],
			[ "sacrificarían" ]
		],
		"7" : [
			[ "sacrificaré" ],
			[ "sacrificarás" ],
			[ "sacrificará" ],
			[ "sacrificaremos" ],
			[ "sacrificaréis" ],
			[ "sacrificarán" ]
		],
		"8" : [
			[ "sacrifique" ],
			[ "sacrifiques" ],
			[ "sacrifique" ],
			[ "sacrifiquemos" ],
			[ "sacrifiquéis" ],
			[ "sacrifiquen" ]
		],
		"9" : [
			[ "sacrificara" ],
			[ "sacrificaras" ],
			[ "sacrificara" ],
			[ "sacrificáramos" ],
			[ "sacrificarais" ],
			[ "sacrificaran" ]
		],
		"10" : [
			[ "sacrificase" ],
			[ "sacrificases" ],
			[ "sacrificase" ],
			[ "sacrificásemos" ],
			[ "sacrificaseis" ],
			[ "sacrificasen" ]
		],
		"11" : [
			[ "sacrificare" ],
			[ "sacrificares" ],
			[ "sacrificare" ],
			[ "sacrificáremos" ],
			[ "sacrificareis" ],
			[ "sacrificaren" ]
		],
		"12" : {
			"1" : [ "sacrifica" ],
			"2" : [ "sacrifique" ],
			"3" : [ "sacrifiquemos" ],
			"4" : [ "sacrificad" ],
			"5" : [ "sacrifiquen" ]
		}
	}
}