{
	"source" : "http:\/\/www.spanishdict.com\/conjugate\/sumergirse",
	"word" : "sumergirse",
	"infinitivo" : "sumergir",
	"translation" : "to dive",
	"gerundio" : [ "sumergiendo" ],
	"participio" : [ "sumergido" ],
	"tenses" : {
		"3" : [
			[ "me sumerjo" ],
			[ "te sumerges" ],
			[ "se sumerge" ],
			[ "nos sumergimos" ],
			[ "os sumergís" ],
			[ "se sumergen" ]
		],
		"4" : [
			[ "me sumergí" ],
			[ "te sumergiste" ],
			[ "se sumergió" ],
			[ "nos sumergimos" ],
			[ "os sumergisteis" ],
			[ "se sumergieron" ]
		],
		"5" : [
			[ "me sumergía" ],
			[ "te sumergías" ],
			[ "se sumergía" ],
			[ "nos sumergíamos" ],
			[ "os sumergíais" ],
			[ "se sumergían" ]
		],
		"6" : [
			[ "me sumergiría" ],
			[ "te sumergirías" ],
			[ "se sumergiría" ],
			[ "nos sumergiríamos" ],
			[ "os sumergiríais" ],
			[ "se sumergirían" ]
		],
		"7" : [
			[ "me sumergiré" ],
			[ "te sumergirás" ],
			[ "se sumergirá" ],
			[ "nos sumergiremos" ],
			[ "os sumergiréis" ],
			[ "se sumergirán" ]
		],
		"8" : [
			[ "me sumerja" ],
			[ "te sumerjas" ],
			[ "se sumerja" ],
			[ "nos sumerjamos" ],
			[ "os sumerjáis" ],
			[ "se sumerjan" ]
		],
		"9" : [
			[ "me sumergiera" ],
			[ "te sumergieras" ],
			[ "se sumergiera" ],
			[ "nos sumergiéramos" ],
			[ "os sumergierais" ],
			[ "se sumergieran" ]
		],
		"10" : [
			[ "me sumergiese" ],
			[ "te sumergieses" ],
			[ "se sumergiese" ],
			[ "nos sumergiésemos" ],
			[ "os sumergieseis" ],
			[ "se sumergiesen" ]
		],
		"11" : [
			[ "me sumergiere" ],
			[ "te sumergieres" ],
			[ "se sumergiere" ],
			[ "nos sumergiéremos" ],
			[ "os sumergiereis" ],
			[ "se sumergieren" ]
		],
		"12" : {
			"1" : [ "sumerge" ],
			"2" : [ "sumerja" ],
			"3" : [ "sumerjamos" ],
			"4" : [ "sumergid" ],
			"5" : [ "sumerjan" ]
		}
	}
}