{
	"source" : "http:\/\/www.spanishdict.com\/conjugate\/eliminarse",
	"word" : "eliminarse",
	"infinitivo" : "eliminar",
	"translation" : "to be eliminated",
	"gerundio" : [ "eliminando" ],
	"participio" : [ "eliminado" ],
	"tenses" : {
		"3" : [
			[ "me elimino" ],
			[ "te eliminas" ],
			[ "se elimina" ],
			[ "nos eliminamos" ],
			[ "os elimináis" ],
			[ "se eliminan" ]
		],
		"4" : [
			[ "me eliminé" ],
			[ "te eliminaste" ],
			[ "se eliminó" ],
			[ "nos eliminamos" ],
			[ "os eliminasteis" ],
			[ "se eliminaron" ]
		],
		"5" : [
			[ "me eliminaba" ],
			[ "te eliminabas" ],
			[ "se eliminaba" ],
			[ "nos eliminábamos" ],
			[ "os eliminabais" ],
			[ "se eliminaban" ]
		],
		"6" : [
			[ "me eliminaría" ],
			[ "te eliminarías" ],
			[ "se eliminaría" ],
			[ "nos eliminaríamos" ],
			[ "os eliminaríais" ],
			[ "se eliminarían" ]
		],
		"7" : [
			[ "me eliminaré" ],
			[ "te eliminarás" ],
			[ "se eliminará" ],
			[ "nos eliminaremos" ],
			[ "os eliminaréis" ],
			[ "se eliminarán" ]
		],
		"8" : [
			[ "me elimine" ],
			[ "te elimines" ],
			[ "se elimine" ],
			[ "nos eliminemos" ],
			[ "os eliminéis" ],
			[ "se eliminen" ]
		],
		"9" : [
			[ "me eliminara" ],
			[ "te eliminaras" ],
			[ "se eliminara" ],
			[ "nos elimináramos" ],
			[ "os eliminarais" ],
			[ "se eliminaran" ]
		],
		"10" : [
			[ "me eliminase" ],
			[ "te eliminases" ],
			[ "se eliminase" ],
			[ "nos eliminásemos" ],
			[ "os eliminaseis" ],
			[ "se eliminasen" ]
		],
		"11" : [
			[ "me eliminare" ],
			[ "te eliminares" ],
			[ "se eliminare" ],
			[ "nos elimináremos" ],
			[ "os eliminareis" ],
			[ "se eliminaren" ]
		],
		"12" : {
			"1" : [ "elimina" ],
			"2" : [ "elimine" ],
			"3" : [ "eliminemos" ],
			"4" : [ "eliminad" ],
			"5" : [ "eliminen" ]
		}
	}
}