{
	"source" : "http:\/\/lema.rae.es\/drae\/srv\/search?val=enjuiciar",
	"word" : "enjuiciar",
	"infinitivo" : "enjuiciar",
	"participio" : [ "enjuiciado" ],
	"gerundio" : [ "enjuiciando" ],
	"tenses" : {
		"3" : [
			[ "enjuicio" ],
			[ "enjuicias", "enjuiciás" ],
			[ "enjuicia" ],
			[ "enjuiciamos" ],
			[ "enjuiciáis", "enjuician" ],
			[ "enjuician" ]
		],
		"4" : [
			[ "enjuicié" ],
			[ "enjuiciaste" ],
			[ "enjuició" ],
			[ "enjuiciamos" ],
			[ "enjuiciasteis", "enjuiciaron" ],
			[ "enjuiciaron" ]
		],
		"5" : [
			[ "enjuiciaba" ],
			[ "enjuiciabas" ],
			[ "enjuiciaba" ],
			[ "enjuiciábamos" ],
			[ "enjuiciabais", "enjuiciaban" ],
			[ "enjuiciaban" ]
		],
		"6" : [
			[ "enjuiciaría" ],
			[ "enjuiciarías" ],
			[ "enjuiciaría" ],
			[ "enjuiciaríamos" ],
			[ "enjuiciaríais", "enjuiciarían" ],
			[ "enjuiciarían" ]
		],
		"7" : [
			[ "enjuiciaré" ],
			[ "enjuiciarás" ],
			[ "enjuiciará" ],
			[ "enjuiciaremos" ],
			[ "enjuiciaréis", "enjuiciarán" ],
			[ "enjuiciarán" ]
		],
		"8" : [
			[ "enjuicie" ],
			[ "enjuicies" ],
			[ "enjuicie" ],
			[ "enjuiciemos" ],
			[ "enjuiciéis", "enjuicien" ],
			[ "enjuicien" ]
		],
		"9" : [
			[ "enjuiciara" ],
			[ "enjuiciaras" ],
			[ "enjuiciara" ],
			[ "enjuiciáramos" ],
			[ "enjuiciarais", "enjuiciaran" ],
			[ "enjuiciaran" ]
		],
		"10" : [
			[ "enjuiciase" ],
			[ "enjuiciases" ],
			[ "enjuiciase" ],
			[ "enjuiciásemos" ],
			[ "enjuiciaseis", "enjuiciasen" ],
			[ "enjuiciasen" ]
		],
		"11" : [
			[ "enjuiciare" ],
			[ "enjuiciares" ],
			[ "enjuiciare" ],
			[ "enjuiciáremos" ],
			[ "enjuiciareis", "enjuiciaren" ],
			[ "enjuiciaren" ]
		],
		"12" : {
			"1" : [ "enjuicia" ],
			"2" : [ "enjuicie" ],
			"3" : [ "enjuiciemos" ],
			"4" : [ "enjuiciad" ],
			"5" : [ "enjuicien" ]
		}
	}
}