{
	"source" : "http:\/\/www.spanishdict.com\/conjugate\/esnifar",
	"word" : "esnifar",
	"infinitivo" : "esnifar",
	"translation" : "to sniff",
	"gerundio" : [ "esnifando" ],
	"participio" : [ "esnifado" ],
	"tenses" : {
		"3" : [
			[ "esnifo" ],
			[ "esnifas" ],
			[ "esnifa" ],
			[ "esnifamos" ],
			[ "esnifáis" ],
			[ "esnifan" ]
		],
		"4" : [
			[ "esnifé" ],
			[ "esnifaste" ],
			[ "esnifó" ],
			[ "esnifamos" ],
			[ "esnifasteis" ],
			[ "esnifaron" ]
		],
		"5" : [
			[ "esnifaba" ],
			[ "esnifabas" ],
			[ "esnifaba" ],
			[ "esnifábamos" ],
			[ "esnifabais" ],
			[ "esnifaban" ]
		],
		"6" : [
			[ "esnifaría" ],
			[ "esnifarías" ],
			[ "esnifaría" ],
			[ "esnifaríamos" ],
			[ "esnifaríais" ],
			[ "esnifarían" ]
		],
		"7" : [
			[ "esnifaré" ],
			[ "esnifarás" ],
			[ "esnifará" ],
			[ "esnifaremos" ],
			[ "esnifaréis" ],
			[ "esnifarán" ]
		],
		"8" : [
			[ "esnife" ],
			[ "esnifes" ],
			[ "esnife" ],
			[ "esnifemos" ],
			[ "esniféis" ],
			[ "esnifen" ]
		],
		"9" : [
			[ "esnifara" ],
			[ "esnifaras" ],
			[ "esnifara" ],
			[ "esnifáramos" ],
			[ "esnifarais" ],
			[ "esnifaran" ]
		],
		"10" : [
			[ "esnifase" ],
			[ "esnifases" ],
			[ "esnifase" ],
			[ "esnifásemos" ],
			[ "esnifaseis" ],
			[ "esnifasen" ]
		],
		"11" : [
			[ "esnifare" ],
			[ "esnifares" ],
			[ "esnifare" ],
			[ "esnifáremos" ],
			[ "esnifareis" ],
			[ "esnifaren" ]
		],
		"12" : {
			"1" : [ "esnifa" ],
			"2" : [ "esnife" ],
			"3" : [ "esnifemos" ],
			"4" : [ "esnifad" ],
			"5" : [ "esnifen" ]
		}
	}
}