{
	"source" : "http:\/\/www.spanishdict.com\/conjugate\/evaporarse",
	"word" : "evaporarse",
	"infinitivo" : "evaporar",
	"gerundio" : [ "evaporando" ],
	"participio" : [ "evaporado" ],
	"tenses" : {
		"3" : [
			[ "me evaporo" ],
			[ "te evaporas" ],
			[ "se evapora" ],
			[ "nos evaporamos" ],
			[ "os evaporáis" ],
			[ "se evaporan" ]
		],
		"4" : [
			[ "me evaporé" ],
			[ "te evaporaste" ],
			[ "se evaporó" ],
			[ "nos evaporamos" ],
			[ "os evaporasteis" ],
			[ "se evaporaron" ]
		],
		"5" : [
			[ "me evaporaba" ],
			[ "te evaporabas" ],
			[ "se evaporaba" ],
			[ "nos evaporábamos" ],
			[ "os evaporabais" ],
			[ "se evaporaban" ]
		],
		"6" : [
			[ "me evaporaría" ],
			[ "te evaporarías" ],
			[ "se evaporaría" ],
			[ "nos evaporaríamos" ],
			[ "os evaporaríais" ],
			[ "se evaporarían" ]
		],
		"7" : [
			[ "me evaporaré" ],
			[ "te evaporarás" ],
			[ "se evaporará" ],
			[ "nos evaporaremos" ],
			[ "os evaporaréis" ],
			[ "se evaporarán" ]
		],
		"8" : [
			[ "me evapore" ],
			[ "te evapores" ],
			[ "se evapore" ],
			[ "nos evaporemos" ],
			[ "os evaporéis" ],
			[ "se evaporen" ]
		],
		"9" : [
			[ "me evaporara" ],
			[ "te evaporaras" ],
			[ "se evaporara" ],
			[ "nos evaporáramos" ],
			[ "os evaporarais" ],
			[ "se evaporaran" ]
		],
		"10" : [
			[ "me evaporase" ],
			[ "te evaporases" ],
			[ "se evaporase" ],
			[ "nos evaporásemos" ],
			[ "os evaporaseis" ],
			[ "se evaporasen" ]
		],
		"11" : [
			[ "me evaporare" ],
			[ "te evaporares" ],
			[ "se evaporare" ],
			[ "nos evaporáremos" ],
			[ "os evaporareis" ],
			[ "se evaporaren" ]
		],
		"12" : {
			"1" : [ "evapora" ],
			"2" : [ "evapore" ],
			"3" : [ "evaporemos" ],
			"4" : [ "evaporad" ],
			"5" : [ "evaporen" ]
		}
	}
}