{
	"source" : "http:\/\/lema.rae.es\/drae\/srv\/search?val=expropiar",
	"word" : "expropiar",
	"infinitivo" : "expropiar",
	"participio" : [ "expropiado" ],
	"gerundio" : [ "expropiando" ],
	"tenses" : {
		"3" : [
			[ "expropio" ],
			[ "expropias", "expropiás" ],
			[ "expropia" ],
			[ "expropiamos" ],
			[ "expropiáis", "expropian" ],
			[ "expropian" ]
		],
		"4" : [
			[ "expropié" ],
			[ "expropiaste" ],
			[ "expropió" ],
			[ "expropiamos" ],
			[ "expropiasteis", "expropiaron" ],
			[ "expropiaron" ]
		],
		"5" : [
			[ "expropiaba" ],
			[ "expropiabas" ],
			[ "expropiaba" ],
			[ "expropiábamos" ],
			[ "expropiabais", "expropiaban" ],
			[ "expropiaban" ]
		],
		"6" : [
			[ "expropiaría" ],
			[ "expropiarías" ],
			[ "expropiaría" ],
			[ "expropiaríamos" ],
			[ "expropiaríais", "expropiarían" ],
			[ "expropiarían" ]
		],
		"7" : [
			[ "expropiaré" ],
			[ "expropiarás" ],
			[ "expropiará" ],
			[ "expropiaremos" ],
			[ "expropiaréis", "expropiarán" ],
			[ "expropiarán" ]
		],
		"8" : [
			[ "expropie" ],
			[ "expropies" ],
			[ "expropie" ],
			[ "expropiemos" ],
			[ "expropiéis", "expropien" ],
			[ "expropien" ]
		],
		"9" : [
			[ "expropiara" ],
			[ "expropiaras" ],
			[ "expropiara" ],
			[ "expropiáramos" ],
			[ "expropiarais", "expropiaran" ],
			[ "expropiaran" ]
		],
		"10" : [
			[ "expropiase" ],
			[ "expropiases" ],
			[ "expropiase" ],
			[ "expropiásemos" ],
			[ "expropiaseis", "expropiasen" ],
			[ "expropiasen" ]
		],
		"11" : [
			[ "expropiare" ],
			[ "expropiares" ],
			[ "expropiare" ],
			[ "expropiáremos" ],
			[ "expropiareis", "expropiaren" ],
			[ "expropiaren" ]
		],
		"12" : {
			"1" : [ "expropia" ],
			"2" : [ "expropie" ],
			"3" : [ "expropiemos" ],
			"4" : [ "expropiad" ],
			"5" : [ "expropien" ]
		}
	}
}